methodtenable/__init__.py
methodtenable/core/__init__.py
methodtenable/core/datetime_utils.py
methodtenable/core/enum.py
methodtenable/core/pydantic_utilities.py
methodtenable/core/serialization.py
methodtenable/py.typed
methodtenable/resources/__init__.py
methodtenable/resources/common/__init__.py
methodtenable/resources/common/secret_config.py
methodtenable/resources/common/severity.py
methodtenable/resources/common/state.py
methodtenable/resources/utils/__init__.py
methodtenable/resources/utils/resources/__init__.py
methodtenable/resources/utils/resources/api/__init__.py
methodtenable/resources/utils/resources/api/resources/__init__.py
methodtenable/resources/utils/resources/api/resources/vm/__init__.py
methodtenable/resources/utils/resources/api/resources/vm/resources/__init__.py
methodtenable/resources/utils/resources/api/resources/vm/resources/asset/__init__.py
methodtenable/resources/utils/resources/api/resources/vm/resources/asset/resources/__init__.py
methodtenable/resources/utils/resources/api/resources/vm/resources/asset/resources/export/__init__.py
methodtenable/resources/utils/resources/api/resources/vm/resources/asset/resources/export/api_vm_asset_export_chunk_request.py
methodtenable/resources/utils/resources/api/resources/vm/resources/asset/resources/export/api_vm_asset_export_chunk_response.py
methodtenable/resources/utils/resources/api/resources/vm/resources/asset/resources/export/api_vm_asset_export_filters.py
methodtenable/resources/utils/resources/api/resources/vm/resources/asset/resources/export/api_vm_asset_export_status_request.py
methodtenable/resources/utils/resources/api/resources/vm/resources/asset/resources/export/api_vm_asset_export_status_response.py
methodtenable/resources/utils/resources/api/resources/vm/resources/asset/resources/export/api_vm_asset_v_2_export_request.py
methodtenable/resources/utils/resources/api/resources/vm/resources/asset/resources/export/api_vm_asset_v_2_export_response.py
methodtenable-0.0.13.dist-info/METADATA
methodtenable-0.0.13.dist-info/WHEEL
methodtenable-0.0.13.dist-info/RECORD
